reflex_pyplot/__init__.py
reflex_pyplot/pyplot.py
reflex_pyplot-0.2.1.dist-info/METADATA
reflex_pyplot-0.2.1.dist-info/WHEEL
reflex_pyplot-0.2.1.dist-info/RECORD
